MANIFEST.in
README.rst
setup.cfg
setup.py
ai/__init__.py
ai/h2o/__init__.py
ai/h2o/sparkling/BackingJar.py
ai/h2o/sparkling/Initializer.py
ai/h2o/sparkling/VersionComponents.py
ai/h2o/sparkling/__init__.py
ai/h2o/sparkling/version.txt
ai/h2o/sparkling/ml/__init__.py
ai/h2o/sparkling/ml/models/H2OBinaryModel.py
ai/h2o/sparkling/ml/models/H2OCoxPHMOJOModel.py
ai/h2o/sparkling/ml/models/H2ODRFMOJOModel.py
ai/h2o/sparkling/ml/models/H2ODeepLearningMOJOModel.py
ai/h2o/sparkling/ml/models/H2OGAMMOJOModel.py
ai/h2o/sparkling/ml/models/H2OGBMMOJOModel.py
ai/h2o/sparkling/ml/models/H2OGLMMOJOModel.py
ai/h2o/sparkling/ml/models/H2OIsolationForestMOJOModel.py
ai/h2o/sparkling/ml/models/H2OKMeansMOJOModel.py
ai/h2o/sparkling/ml/models/H2OMOJOModel.py
ai/h2o/sparkling/ml/models/H2OMOJOModelBase.py
ai/h2o/sparkling/ml/models/H2OMOJOPipelineModel.py
ai/h2o/sparkling/ml/models/H2OMOJOSettings.py
ai/h2o/sparkling/ml/models/H2OTargetEncoderMOJOModel.py
ai/h2o/sparkling/ml/models/H2OTargetEncoderModel.py
ai/h2o/sparkling/ml/models/H2OXGBoostMOJOModel.py
ai/h2o/sparkling/ml/models/__init__.py
ai/h2o/sparkling/ml/params/H2OAutoMLParams.py
ai/h2o/sparkling/ml/params/H2OBaseMOJOParams.py
ai/h2o/sparkling/ml/params/H2OCommonParams.py
ai/h2o/sparkling/ml/params/H2OGridSearchParams.py
ai/h2o/sparkling/ml/params/H2OMOJOModelParams.py
ai/h2o/sparkling/ml/params/H2OTargetEncoderMOJOParams.py
ai/h2o/sparkling/ml/params/H2OTreeBasedSupervisedMOJOParams.py
ai/h2o/sparkling/ml/params/H2OTypeConverters.py
ai/h2o/sparkling/ml/params/HasBetaConstraints.py
ai/h2o/sparkling/ml/params/HasBlendingDataFrame.py
ai/h2o/sparkling/ml/params/HasCalibrationDataFrame.py
ai/h2o/sparkling/ml/params/HasDeprecatedVariableImportances.py
ai/h2o/sparkling/ml/params/HasDeprecatedVariableImportancesOnMOJO.py
ai/h2o/sparkling/ml/params/HasGamCols.py
ai/h2o/sparkling/ml/params/HasGamColsOnMOJO.py
ai/h2o/sparkling/ml/params/HasIgnoredCols.py
ai/h2o/sparkling/ml/params/HasIgnoredColsOnMOJO.py
h2o_pysparkling_scoring_2.1.egg-info/PKG-INFO
h2o_pysparkling_scoring_2.1.egg-info/SOURCES.txt
h2o_pysparkling_scoring_2.1.egg-info/dependency_links.txt
h2o_pysparkling_scoring_2.1.egg-info/top_level.txt
